smoothiepy-0.1.1.dist-info/METADATA
smoothiepy-0.1.1.dist-info/WHEEL
smoothiepy-0.1.1.dist-info/entry_points.txt
smoothiepy-0.1.1.dist-info/licenses/LICENSE
smoothiepy/__init__.py
smoothiepy/core.py
smoothiepy/filter/__init__.py
smoothiepy/filter/basefilter.py
smoothiepy/filter/filter1d.py
smoothiepy/filter/filter2d.py
smoothiepy/filter/filter2d_naive.py
smoothiepy/smoother/__init__.py
smoothiepy/smoother/builder.py
smoothiepy/smoother/smoother.py
smoothiepy-0.1.1.dist-info/RECORD
