Metadata-Version: 2.4
Name: smoothiepy
Version: 0.1.1
Summary: Smooth real-time data streams like eye tracking or sensor input with this lightweight package.
Keywords: smoothing,data-smoothing,signal-filter,signal-processing,noise-reduction,real-time,low-latency,live-data,online-processing,streaming-data,data-cleaning,data-filtering,preprocessing,adaptive-filter,ema,moving-average,median-filter,gaussian-smoothing,time-series,trend-analysis,rolling-average,forecasting,financial-data,stock-market,price-smoothing,volatility-reduction,algorithmic-trading,market-data,quantitative-analysis,data-denoising,eye-tracking,gaze-tracking,gaze-analysis,saccade-fil
Author-Email: Timo Seyfarth <timo@seyfarth.dev>
License-Expression: LGPL-3.0-or-later
License-File: LICENSE
Classifier: Programming Language :: Python :: 3
Classifier: Programming Language :: Python :: 3.10
Classifier: Programming Language :: Python :: 3.11
Classifier: Programming Language :: Python :: 3.12
Classifier: Programming Language :: Python :: 3.13
Classifier: Programming Language :: Python :: 3.14
Classifier: Operating System :: OS Independent
Classifier: Development Status :: 3 - Alpha
Classifier: Intended Audience :: Developers
Classifier: Intended Audience :: Science/Research
Classifier: Intended Audience :: Education
Classifier: Natural Language :: English
Classifier: Topic :: Scientific/Engineering
Classifier: Topic :: Scientific/Engineering :: Human Machine Interfaces
Classifier: Topic :: Scientific/Engineering :: Information Analysis
Classifier: Topic :: Software Development :: Libraries :: Python Modules
Project-URL: Homepage, https://github.com/timoseyfarth/smoothiepy
Project-URL: Documentation, https://github.com/timoseyfarth/smoothiepy/wiki
Project-URL: Issues, https://github.com/timoseyfarth/smoothiepy/issues
Requires-Python: >=3.10.0
Requires-Dist: numpy>=2.1.0
Provides-Extra: dev
Requires-Dist: pytest~=8.3.5; extra == "dev"
Requires-Dist: pylint>=3.3.7; extra == "dev"
